{
  "id": "d6db3720-e482-4935-851f-2c8a7ec3cc27",
  "name": "Hermes News Local",
  "values": [
    {
      "key": "base_url",
      "value": "http://localhost:8080",
      "type": "default",
      "enabled": true
    },
    {
      "key": "evolution_base_url",
      "value": "http://localhost:8081",
      "type": "default",
      "enabled": true
    },
    {
      "key": "evolution_api_key",
      "value": "change-me-local-only",
      "type": "secret",
      "enabled": true
    },
    {
      "key": "evolution_instance",
      "value": "hermes-local",
      "type": "default",
      "enabled": true
    },
    {
      "key": "evolution_recipient",
      "value": "",
      "type": "default",
      "enabled": true
    },
    {
      "key": "request_guid",
      "value": "",
      "type": "default",
      "enabled": true
    },
    {
      "key": "request_timestamp",
      "value": "",
      "type": "default",
      "enabled": true
    },
    {
      "key": "request_iso_timestamp",
      "value": "",
      "type": "default",
      "enabled": true
    },
    {
      "key": "last_digest_message",
      "value": "",
      "type": "default",
      "enabled": true
    }
  ],
  "_postman_variable_scope": "environment",
  "_postman_exported_using": "Codex"
}
